[
   {
      "id":223,
      "name":"CLIENTS",
      "type":2,
      "dn":"OU=CLIENTS,DC=ad,DC=labdomain,DC=com",
      "is_user_selected":true,
      "guid":"d9b2392d-01e5-4e8b-98bf-26fb85a3399c",
      "full_path":"ad.labdomain.com/CLIENTS",
      "parent_ids":[
         227
      ],
      "has_child":0,
      "blocked":false,
      "policy_id":"None",
      "domain_id":3,
      "policy_name":"None",
      "telemetry_server_list_id":"None",
      "telemetry_server_list_name":"None",
      "total_devices":2,
      "domain_type":1
   },
   {
      "id":224,
      "name":"VPN_USERS",
      "type":4,
      "dn":"CN=VPN_USERS,OU=GROUPS,DC=ad,DC=labdomain,DC=com",
      "is_user_selected":true,
      "guid":"a79fcd99-07e2-4c75-a615-58043fd244da",
      "full_path":"ad.labdomain.com/GROUPS/VPN_USERS",
      "parent_ids":[
         227
      ],
      "has_child":0,
      "blocked":false,
      "policy_id":"None",
      "domain_id":3,
      "policy_name":"None",
      "telemetry_server_list_id":"None",
      "telemetry_server_list_name":"None",
      "total_devices":0,
      "domain_type":1
   },
   {
      "id":225,
      "name":"ZTNA_USERS",
      "type":4,
      "dn":"CN=ZTNA_USERS,OU=GROUPS,DC=ad,DC=labdomain,DC=com",
      "is_user_selected":true,
      "guid":"83658fae-a526-4d9e-8030-8193a7fa0198",
      "full_path":"ad.labdomain.com/GROUPS/ZTNA_USERS",
      "parent_ids":[
         227
      ],
      "has_child":0,
      "blocked":false,
      "policy_id":"None",
      "domain_id":3,
      "policy_name":"None",
      "telemetry_server_list_id":"None",
      "telemetry_server_list_name":"None",
      "total_devices":0,
      "domain_type":1
   },
   {
      "id":226,
      "name":"SERVERS",
      "type":2,
      "dn":"OU=SERVERS,DC=ad,DC=labdomain,DC=com",
      "is_user_selected":true,
      "guid":"015eb230-26f7-4a10-bde7-df92b0891848",
      "full_path":"ad.labdomain.com/SERVERS",
      "parent_ids":[
         227
      ],
      "has_child":1,
      "blocked":false,
      "policy_id":"None",
      "domain_id":3,
      "policy_name":"None",
      "telemetry_server_list_id":"None",
      "telemetry_server_list_name":"None",
      "total_devices":1,
      "domain_type":1
   }
]